pyproject.toml
setup.py
pttoolkit/__init__.py
pttoolkit/pttoolkit.py
pttoolkit.egg-info/PKG-INFO
pttoolkit.egg-info/SOURCES.txt
pttoolkit.egg-info/dependency_links.txt
pttoolkit.egg-info/top_level.txt