Metadata-Version: 2.1
Name: pttoolkit
Version: 0.1.1
Summary: An example Python package
Author: FunkaClau
Author-email: 
